{"version": "https://jsonfeed.org/version/1", "title": "Jiegec's Knowledge Base", "home_page_url": "https://jia.je/kb/", "feed_url": "https://jia.je/kb/feed_json_created.json", "description": "Knowledge Base of @jiegec", "icon": null, "authors": [], "language": "en", "items": [{"id": "https://jia.je/kb/software/cfi.html", "url": "https://jia.je/kb/software/cfi.html", "title": "\u63a7\u5236\u6d41\u5b8c\u6574\u6027 Control Flow Integrity", "content_html": "<h1>\u63a7\u5236\u6d41\u5b8c\u6574\u6027 Control Flow Integrity</h1>\n<h2>\u76ee\u7684\u5730\u5740\u68c0\u67e5</h2>\n<p>\u4e00\u7c7b\u5e38\u89c1\u7684 CFI \u673a\u5236\u662f\u68c0\u67e5\u95f4\u63a5\u5206\u652f\uff08call/jmp reg\uff09\u7684\u76ee\u7684\u5730\u5740\uff0c\u662f\u5426\u843d\u5230\u9884\u671f\u7684\u4f4d\u7f6e\u4e0a\uff0c\u6bd4\u5982\u51fd\u6570\u7684\u5f00\u5934\u3002\u8fd9\u4e2a\u673a\u5236\u4e3b\u8981\u9632\u6b62\u7684\u662f ROP gadget\uff0c\u5373\u4ece\u73b0\u6709\u6307\u4ee4\u7684\u4e2d\u95f4\u67d0\u4e2a\u4f4d\u7f6e\u5f00\u59cb\u6267\u884c\u4e00\u6bb5\u4ee3\u7801\uff0c\u4ece\u800c\u5b9e\u73b0\u653b\u51fb\u8005\u60f3\u8981\u7684\u6548...</p>", "image": "https://jia.je/kb/assets/images/social/software/cfi.png", "date_published": "2024-12-13T01:56:23+00:00", "authors": [], "tags": null}, {"id": "https://jia.je/kb/en/software/cfi.html", "url": "https://jia.je/kb/en/software/cfi.html", "title": "\u63a7\u5236\u6d41\u5b8c\u6574\u6027 Control Flow Integrity", "content_html": "<h1>\u63a7\u5236\u6d41\u5b8c\u6574\u6027 Control Flow Integrity</h1>\n<h2>\u76ee\u7684\u5730\u5740\u68c0\u67e5</h2>\n<p>\u4e00\u7c7b\u5e38\u89c1\u7684 CFI \u673a\u5236\u662f\u68c0\u67e5\u95f4\u63a5\u5206\u652f\uff08call/jmp reg\uff09\u7684\u76ee\u7684\u5730\u5740\uff0c\u662f\u5426\u843d\u5230\u9884\u671f\u7684\u4f4d\u7f6e\u4e0a\uff0c\u6bd4\u5982\u51fd\u6570\u7684\u5f00\u5934\u3002\u8fd9\u4e2a\u673a\u5236\u4e3b\u8981\u9632\u6b62\u7684\u662f ROP gadget\uff0c\u5373\u4ece\u73b0\u6709\u6307\u4ee4\u7684\u4e2d\u95f4\u67d0\u4e2a\u4f4d\u7f6e\u5f00\u59cb\u6267\u884c\u4e00\u6bb5\u4ee3\u7801\uff0c\u4ece\u800c\u5b9e\u73b0\u653b\u51fb\u8005\u60f3\u8981\u7684\u6548...</p>", "image": "https://jia.je/kb/assets/images/social/software/cfi.png", "date_published": "2024-12-13T01:56:23+00:00", "authors": [], "tags": null}, {"id": "https://jia.je/kb/software/cfi.html", "url": "https://jia.je/kb/software/cfi.html", "title": "\u63a7\u5236\u6d41\u5b8c\u6574\u6027 Control Flow Integrity", "content_html": "<h1>\u63a7\u5236\u6d41\u5b8c\u6574\u6027 Control Flow Integrity</h1>\n<h2>\u76ee\u7684\u5730\u5740\u68c0\u67e5</h2>\n<p>\u4e00\u7c7b\u5e38\u89c1\u7684 CFI \u673a\u5236\u662f\u68c0\u67e5\u95f4\u63a5\u5206\u652f\uff08call/jmp reg\uff09\u7684\u76ee\u7684\u5730\u5740\uff0c\u662f\u5426\u843d\u5230\u9884\u671f\u7684\u4f4d\u7f6e\u4e0a\uff0c\u6bd4\u5982\u51fd\u6570\u7684\u5f00\u5934\u3002\u8fd9\u4e2a\u673a\u5236\u4e3b\u8981\u9632\u6b62\u7684\u662f ROP gadget\uff0c\u5373\u4ece\u73b0\u6709\u6307\u4ee4\u7684\u4e2d\u95f4\u67d0\u4e2a\u4f4d\u7f6e\u5f00\u59cb\u6267\u884c\u4e00\u6bb5\u4ee3\u7801\uff0c\u4ece\u800c\u5b9e\u73b0\u653b\u51fb\u8005\u60f3\u8981\u7684\u6548...</p>", "image": "https://jia.je/kb/assets/images/social/software/cfi.png", "date_published": "2024-12-13T01:56:23+00:00", "authors": [], "tags": null}, {"id": "https://jia.je/kb/software/linux_scheduler.html", "url": "https://jia.je/kb/software/linux_scheduler.html", "title": "Linux Scheduler", "content_html": "<h1>Linux Scheduler</h1>\n<h2>CFS Completely Fair Scheduler</h2>\n<p>\u6587\u6863\uff1a<a href=\"https://docs.kernel.org/scheduler/sched-design-CFS.html\">CFS Scheduler</a></p>\n<p>\u8bbe\u8ba1\u76ee\u6807\uff1a\u5efa\u6a21\u4e00\u4e2a\u7406\u60f3\u7684\u591a\u4efb\u52a1 CPU\uff0c\u5b83\u4ee5\u76f8\u540c\u7684\u901f\u5ea6...</p>", "image": "https://jia.je/kb/assets/images/social/software/linux_scheduler.png", "date_published": "2024-10-31T09:25:27+00:00", "authors": [], "tags": null}, {"id": "https://jia.je/kb/en/software/linux_scheduler.html", "url": "https://jia.je/kb/en/software/linux_scheduler.html", "title": "Linux Scheduler", "content_html": "<h1>Linux Scheduler</h1>\n<h2>CFS Completely Fair Scheduler</h2>\n<p>\u6587\u6863\uff1a<a href=\"https://docs.kernel.org/scheduler/sched-design-CFS.html\">CFS Scheduler</a></p>\n<p>\u8bbe\u8ba1\u76ee\u6807\uff1a\u5efa\u6a21\u4e00\u4e2a\u7406\u60f3\u7684\u591a\u4efb\u52a1 CPU\uff0c\u5b83\u4ee5\u76f8\u540c\u7684\u901f\u5ea6...</p>", "image": "https://jia.je/kb/assets/images/social/software/linux_scheduler.png", "date_published": "2024-10-31T09:25:27+00:00", "authors": [], "tags": null}, {"id": "https://jia.je/kb/software/linux_scheduler.html", "url": "https://jia.je/kb/software/linux_scheduler.html", "title": "Linux Scheduler", "content_html": "<h1>Linux Scheduler</h1>\n<h2>CFS Completely Fair Scheduler</h2>\n<p>\u6587\u6863\uff1a<a href=\"https://docs.kernel.org/scheduler/sched-design-CFS.html\">CFS Scheduler</a></p>\n<p>\u8bbe\u8ba1\u76ee\u6807\uff1a\u5efa\u6a21\u4e00\u4e2a\u7406\u60f3\u7684\u591a\u4efb\u52a1 CPU\uff0c\u5b83\u4ee5\u76f8\u540c\u7684\u901f\u5ea6...</p>", "image": "https://jia.je/kb/assets/images/social/software/linux_scheduler.png", "date_published": "2024-10-31T09:25:27+00:00", "authors": [], "tags": null}, {"id": "https://jia.je/kb/hardware/nand_flash.html", "url": "https://jia.je/kb/hardware/nand_flash.html", "title": "NAND Flash", "content_html": "<h1>NAND Flash</h1>\n<h2>\u7ed3\u6784</h2>\n<p>NAND Flash \u5206\u5982\u4e0b\u5c42\u6b21\uff1a</p>\n<ul>\n<li>Package/Chip</li>\n<li>Die</li>\n<li>Plane</li>\n<li>Block\uff1aErase \u7684\u7c92\u5ea6</li>\n<li>Page\uff1aProgram/Read \u7684\u7c92\u5ea6</li>\n</ul>\n<p>Erase\uff1a\u628a\u6574\u4e2a Block \u7684\u6570\u636e\u5199\u6210\u5168 1</p>\n<p>Program\uff1a\u628a Page \u7684\u67d0\u4e9b ...</p>", "image": "https://jia.je/kb/assets/images/social/hardware/nand_flash.png", "date_published": "2024-10-06T05:06:22+00:00", "authors": [], "tags": null}, {"id": "https://jia.je/kb/en/hardware/nand_flash.html", "url": "https://jia.je/kb/en/hardware/nand_flash.html", "title": "NAND Flash", "content_html": "<h1>NAND Flash</h1>\n<h2>\u7ed3\u6784</h2>\n<p>NAND Flash \u5206\u5982\u4e0b\u5c42\u6b21\uff1a</p>\n<ul>\n<li>Package/Chip</li>\n<li>Die</li>\n<li>Plane</li>\n<li>Block\uff1aErase \u7684\u7c92\u5ea6</li>\n<li>Page\uff1aProgram/Read \u7684\u7c92\u5ea6</li>\n</ul>\n<p>Erase\uff1a\u628a\u6574\u4e2a Block \u7684\u6570\u636e\u5199\u6210\u5168 1</p>\n<p>Program\uff1a\u628a Page \u7684\u67d0\u4e9b ...</p>", "image": "https://jia.je/kb/assets/images/social/hardware/nand_flash.png", "date_published": "2024-10-06T05:06:22+00:00", "authors": [], "tags": null}, {"id": "https://jia.je/kb/hardware/nand_flash.html", "url": "https://jia.je/kb/hardware/nand_flash.html", "title": "NAND Flash", "content_html": "<h1>NAND Flash</h1>\n<h2>\u7ed3\u6784</h2>\n<p>NAND Flash \u5206\u5982\u4e0b\u5c42\u6b21\uff1a</p>\n<ul>\n<li>Package/Chip</li>\n<li>Die</li>\n<li>Plane</li>\n<li>Block\uff1aErase \u7684\u7c92\u5ea6</li>\n<li>Page\uff1aProgram/Read \u7684\u7c92\u5ea6</li>\n</ul>\n<p>Erase\uff1a\u628a\u6574\u4e2a Block \u7684\u6570\u636e\u5199\u6210\u5168 1</p>\n<p>Program\uff1a\u628a Page \u7684\u67d0\u4e9b ...</p>", "image": "https://jia.je/kb/assets/images/social/hardware/nand_flash.png", "date_published": "2024-10-06T05:06:22+00:00", "authors": [], "tags": null}, {"id": "https://jia.je/kb/hardware/cpu_microarchitecture.html", "url": "https://jia.je/kb/hardware/cpu_microarchitecture.html", "title": "CPU \u5fae\u67b6\u6784\u5206\u6790", "content_html": "<h1>CPU \u5fae\u67b6\u6784\u5206\u6790</h1>\n<h2>\u590d\u73b0 Intel \u6761\u4ef6\u5206\u652f\u9884\u6d4b\u5668\u9006\u5411\u8bba\u6587</h2>\n<h3>\u80cc\u666f</h3>\n<p>\u6700\u8fd1\u770b\u5230\u4e00\u7cfb\u5217\u5bf9 Intel \u5206\u652f\u9884\u6d4b\u5668\u7684\u9006\u5411\u4ee5\u53ca\u5bf9\u5e94\u7684\u653b\u9632\u7684\u8bba\u6587\uff1a</p>\n<ul>\n<li>[Half&amp;Half: Demystifying Intel's Directional Branch Predictors for Fast, ...</li>\n</ul>", "image": "https://jia.je/kb/assets/images/social/hardware/cpu_microarchitecture.png", "date_published": "2024-07-10T14:47:08+00:00", "authors": [], "tags": null}, {"id": "https://jia.je/kb/en/hardware/cpu_microarchitecture.html", "url": "https://jia.je/kb/en/hardware/cpu_microarchitecture.html", "title": "CPU \u5fae\u67b6\u6784\u5206\u6790", "content_html": "<h1>CPU \u5fae\u67b6\u6784\u5206\u6790</h1>\n<h2>\u590d\u73b0 Intel \u6761\u4ef6\u5206\u652f\u9884\u6d4b\u5668\u9006\u5411\u8bba\u6587</h2>\n<h3>\u80cc\u666f</h3>\n<p>\u6700\u8fd1\u770b\u5230\u4e00\u7cfb\u5217\u5bf9 Intel \u5206\u652f\u9884\u6d4b\u5668\u7684\u9006\u5411\u4ee5\u53ca\u5bf9\u5e94\u7684\u653b\u9632\u7684\u8bba\u6587\uff1a</p>\n<ul>\n<li>[Half&amp;Half: Demystifying Intel's Directional Branch Predictors for Fast, ...</li>\n</ul>", "image": "https://jia.je/kb/assets/images/social/hardware/cpu_microarchitecture.png", "date_published": "2024-07-10T14:47:08+00:00", "authors": [], "tags": null}, {"id": "https://jia.je/kb/hardware/cpu_microarchitecture.html", "url": "https://jia.je/kb/hardware/cpu_microarchitecture.html", "title": "CPU \u5fae\u67b6\u6784\u5206\u6790", "content_html": "<h1>CPU \u5fae\u67b6\u6784\u5206\u6790</h1>\n<h2>\u590d\u73b0 Intel \u6761\u4ef6\u5206\u652f\u9884\u6d4b\u5668\u9006\u5411\u8bba\u6587</h2>\n<h3>\u80cc\u666f</h3>\n<p>\u6700\u8fd1\u770b\u5230\u4e00\u7cfb\u5217\u5bf9 Intel \u5206\u652f\u9884\u6d4b\u5668\u7684\u9006\u5411\u4ee5\u53ca\u5bf9\u5e94\u7684\u653b\u9632\u7684\u8bba\u6587\uff1a</p>\n<ul>\n<li>[Half&amp;Half: Demystifying Intel's Directional Branch Predictors for Fast, ...</li>\n</ul>", "image": "https://jia.je/kb/assets/images/social/hardware/cpu_microarchitecture.png", "date_published": "2024-07-10T14:47:08+00:00", "authors": [], "tags": null}, {"id": "https://jia.je/kb/hardware/conditional_branch_predictor.html", "url": "https://jia.je/kb/hardware/conditional_branch_predictor.html", "title": "\u6761\u4ef6\u5206\u652f\u9884\u6d4b\u5668", "content_html": "<h1>\u6761\u4ef6\u5206\u652f\u9884\u6d4b\u5668</h1>\n<p>\u6761\u4ef6\u5206\u652f\u9884\u6d4b\u5668\u8d1f\u8d23\u9884\u6d4b\u6761\u4ef6\u5206\u652f\u7684\u8df3\u8f6c\u65b9\u5411\uff1a\u8df3\u8f6c\uff08Taken\uff09\u6216\u8005\u4e0d\u8df3\u8f6c\uff08Not Taken\uff09\u3002</p>\n<h2>Static predictor</h2>\n<p>\u53ea\u6839\u636e\u6307\u4ee4\u672c\u8eab\u7684\u7c7b\u578b\uff08\u6216\u8005 hint\uff09\u8fdb\u884c\u5206\u652f\u9884\u6d4b\u3002</p>\n<h2>Bimodal predictor</h2>\n<p>\u5bf9\u5206\u652f\u5730\u5740\u6c42 hash\uff0c\u5f97\u5230\u7684 hash \u53d6\u6a21\u4f5c\u4e3a ...</p>", "image": "https://jia.je/kb/assets/images/social/hardware/conditional_branch_predictor.png", "date_published": "2024-07-10T06:12:46+00:00", "authors": [], "tags": null}, {"id": "https://jia.je/kb/en/hardware/conditional_branch_predictor.html", "url": "https://jia.je/kb/en/hardware/conditional_branch_predictor.html", "title": "\u6761\u4ef6\u5206\u652f\u9884\u6d4b\u5668", "content_html": "<h1>\u6761\u4ef6\u5206\u652f\u9884\u6d4b\u5668</h1>\n<p>\u6761\u4ef6\u5206\u652f\u9884\u6d4b\u5668\u8d1f\u8d23\u9884\u6d4b\u6761\u4ef6\u5206\u652f\u7684\u8df3\u8f6c\u65b9\u5411\uff1a\u8df3\u8f6c\uff08Taken\uff09\u6216\u8005\u4e0d\u8df3\u8f6c\uff08Not Taken\uff09\u3002</p>\n<h2>Static predictor</h2>\n<p>\u53ea\u6839\u636e\u6307\u4ee4\u672c\u8eab\u7684\u7c7b\u578b\uff08\u6216\u8005 hint\uff09\u8fdb\u884c\u5206\u652f\u9884\u6d4b\u3002</p>\n<h2>Bimodal predictor</h2>\n<p>\u5bf9\u5206\u652f\u5730\u5740\u6c42 hash\uff0c\u5f97\u5230\u7684 hash \u53d6\u6a21\u4f5c\u4e3a ...</p>", "image": "https://jia.je/kb/assets/images/social/hardware/conditional_branch_predictor.png", "date_published": "2024-07-10T06:12:46+00:00", "authors": [], "tags": null}, {"id": "https://jia.je/kb/hardware/conditional_branch_predictor.html", "url": "https://jia.je/kb/hardware/conditional_branch_predictor.html", "title": "\u6761\u4ef6\u5206\u652f\u9884\u6d4b\u5668", "content_html": "<h1>\u6761\u4ef6\u5206\u652f\u9884\u6d4b\u5668</h1>\n<p>\u6761\u4ef6\u5206\u652f\u9884\u6d4b\u5668\u8d1f\u8d23\u9884\u6d4b\u6761\u4ef6\u5206\u652f\u7684\u8df3\u8f6c\u65b9\u5411\uff1a\u8df3\u8f6c\uff08Taken\uff09\u6216\u8005\u4e0d\u8df3\u8f6c\uff08Not Taken\uff09\u3002</p>\n<h2>Static predictor</h2>\n<p>\u53ea\u6839\u636e\u6307\u4ee4\u672c\u8eab\u7684\u7c7b\u578b\uff08\u6216\u8005 hint\uff09\u8fdb\u884c\u5206\u652f\u9884\u6d4b\u3002</p>\n<h2>Bimodal predictor</h2>\n<p>\u5bf9\u5206\u652f\u5730\u5740\u6c42 hash\uff0c\u5f97\u5230\u7684 hash \u53d6\u6a21\u4f5c\u4e3a ...</p>", "image": "https://jia.je/kb/assets/images/social/hardware/conditional_branch_predictor.png", "date_published": "2024-07-10T06:12:46+00:00", "authors": [], "tags": null}, {"id": "https://jia.je/kb/software/spark.html", "url": "https://jia.je/kb/software/spark.html", "title": "Apache Spark", "content_html": "<h1>Apache Spark</h1>\n<h2>Installation</h2>\n<p>Follow https://spark.apache.org/downloads.html, download and extract</p>\n<h2>Usage</h2>\n<ul>\n<li>REPL: pyspark(Python), spark-shell(Scala)\n...</li>\n</ul>", "image": "https://jia.je/kb/assets/images/social/software/spark.png", "date_published": "2024-06-22T09:58:19+00:00", "authors": [], "tags": null}, {"id": "https://jia.je/kb/en/software/spark.html", "url": "https://jia.je/kb/en/software/spark.html", "title": "Apache Spark", "content_html": "<h1>Apache Spark</h1>\n<h2>Installation</h2>\n<p>Follow https://spark.apache.org/downloads.html, download and extract</p>\n<h2>Usage</h2>\n<ul>\n<li>REPL: pyspark(Python), spark-shell(Scala)\n...</li>\n</ul>", "image": "https://jia.je/kb/assets/images/social/software/spark.png", "date_published": "2024-06-22T09:58:19+00:00", "authors": [], "tags": null}, {"id": "https://jia.je/kb/software/spark.html", "url": "https://jia.je/kb/software/spark.html", "title": "Apache Spark", "content_html": "<h1>Apache Spark</h1>\n<h2>Installation</h2>\n<p>Follow https://spark.apache.org/downloads.html, download and extract</p>\n<h2>Usage</h2>\n<ul>\n<li>REPL: pyspark(Python), spark-shell(Scala)\n...</li>\n</ul>", "image": "https://jia.je/kb/assets/images/social/software/spark.png", "date_published": "2024-06-22T09:58:19+00:00", "authors": [], "tags": null}, {"id": "https://jia.je/kb/software/postgresql.html", "url": "https://jia.je/kb/software/postgresql.html", "title": "PostgreSQL", "content_html": "<h1>PostgreSQL</h1>\n<h2>SQL Language</h2>\n<h3>Common statements</h3>\n<ul>\n<li>CREATE TABLE</li>\n<li>INSERT INTO table [columns] VALUES (value1, value2)</li>\n<li>COPY table FROM</li>\n<li>SELECT columns...</li>\n</ul>", "image": "https://jia.je/kb/assets/images/social/software/postgresql.png", "date_published": "2024-06-16T11:18:48+00:00", "authors": [], "tags": null}, {"id": "https://jia.je/kb/en/software/postgresql.html", "url": "https://jia.je/kb/en/software/postgresql.html", "title": "PostgreSQL", "content_html": "<h1>PostgreSQL</h1>\n<h2>SQL Language</h2>\n<h3>Common statements</h3>\n<ul>\n<li>CREATE TABLE</li>\n<li>INSERT INTO table [columns] VALUES (value1, value2)</li>\n<li>COPY table FROM</li>\n<li>SELECT columns...</li>\n</ul>", "image": "https://jia.je/kb/assets/images/social/software/postgresql.png", "date_published": "2024-06-16T11:18:48+00:00", "authors": [], "tags": null}]}